argteller/__init__.py
argteller/argteller.py
argteller/tree/__init__.py
argteller/tree/base_node.py
argteller/tree/nodes.py
argteller/tree/tree_parser.py
argteller-0.0b21.dist-info/LICENSE
argteller-0.0b21.dist-info/METADATA
argteller-0.0b21.dist-info/WHEEL
argteller-0.0b21.dist-info/top_level.txt
argteller-0.0b21.dist-info/RECORD
