Metadata-Version: 2.1
Name: argteller
Version: 0.0b21
Summary: Decorator for stylized interactive constructor using DSL and parser.
Home-page: https://github.com/mozjay0619/argteller
Author: Jay Kim
License: DSB 3-clause
Platform: UNKNOWN
